[
    ["MultiFieldBlobs", [
        {"name":"etusivusisältö","fields":"{\"__fields\":[{\"id\":1,\"widget\":{\"name\":\"textField\",\"args\":{}},\"name\":\"Otsikko\"},{\"id\":2,\"widget\":{\"name\":\"textArea\",\"args\":{}},\"name\":\"Teksti\"}],\"Otsikko\":\"Hei maailma!\",\"Teksti\":\"Lorem ipsum corundum ingot.\"}"},
        {"name":"globalFooter","fields":"{\"__fields\":[{\"id\":1,\"widget\":{\"name\":\"textArea\",\"args\":{}},\"name\":\"Teksti\"},{\"id\":2,\"widget\":{\"name\":\"textArea\",\"args\":{}},\"name\":\"Tagline\"}],\"Teksti\":\"Footerin teksti.\",\"Tagline\":\"Footerin tagline.\"}"}
    ]],
    ["Articles", [
        {"slug":"artikkeli-1","title":"Artikkeli 1","body":"Terve artikkelista 1"},
        {"slug":"artikkeli-2","title":"Artikkeli 2","body":"Terve artikkelista 2"},
        {"slug":"artikkeli-3","title":"Artikkeli 3","body":"Terve artikkelista 3"}
    ]]
]
